fastlevenshtein-0.2.1.dist-info/METADATA
fastlevenshtein-0.2.1.dist-info/WHEEL
fastlevenshtein/__init__.py
fastlevenshtein/fastlevenshtein.cpython-39-x86_64-linux-gnu.so
fastlevenshtein-0.2.1.dist-info/RECORD
