Metadata-Version: 2.1
Name: fastlevenshtein
Version: 0.2.1
Classifier: License :: OSI Approved :: GNU General Public License (GPL) 
Classifier: Development Status :: 3 - Alpha
Classifier: Intended Audience :: Developers
Classifier: Programming Language :: Python
Classifier: Programming Language :: Rust
Classifier: Operating System :: POSIX :: Linux
Summary: A really fast levenshtein distance implementation, with early exit.
Home-Page: https://github.com/thibaultbl/fastlevenshtein
Author: ThibaultB
Project-URL: Source Code, https://github.com/thibaultbl/fastlevenshtein
